{"title": ["Ni nanoparticles supported on carbon as efficient catalysts for the hydrolysis of ammonia borane"], "authors": ["Limin\u00a0Zhou", "Tianran\u00a0Zhang", "Zhanliang\u00a0Tao", "Jun\u00a0Chen"], "doi": ["https://doi.org/10.1007/s12274-014-0438-7"], "abstract": [], "text": [], "figures": ["<div class=\"MediaObject\" id=\"MOESM1\"><a href=\"https://static-content.springer.com/image/art%3A10.1007%2Fs12274-014-0438-7/MediaObjects/12274_2014_438_Fig1_HTML.gif\" target=\"_blank\" rel=\"noopener\"><span class=\"u-screenreader-only\">Open image in new window</span><img src=\"https://static-content.springer.com/image/art%3A10.1007%2Fs12274-014-0438-7/MediaObjects/12274_2014_438_Fig1_HTML.gif\" alt=\"\"></a></div>"]}
